fortunecookiecravaggio/__init__.py
fortunecookiecravaggio/__main__.py
fortunecookiecravaggio/fortune.py
fortunecookiecravaggio/fortunes.txt
fortunecookiecravaggio-1.0.4.dist-info/licenses/LICENSE
fortunecookiecravaggio-1.0.4.dist-info/METADATA
fortunecookiecravaggio-1.0.4.dist-info/WHEEL
fortunecookiecravaggio-1.0.4.dist-info/top_level.txt
fortunecookiecravaggio-1.0.4.dist-info/RECORD
