Metadata-Version: 2.4
Name: fortunecookiecravaggio
Version: 1.0.4
Summary: A package that generates “fortune cookie” messages, programming wisdom, or absurd advice when called.
Home-page: https://github.com/software-students-spring2025/3-python-package-cravaggio
Author: Cravaggio
Author-email: Nina Li <jl13999@nyu.edu>, Sirui Wang <sw5546@nyu.edu>, Bohan Yin <by2179@nyu.edu>, Nick Zhu <xz4687@nyu.edu>
License:                     GNU GENERAL PUBLIC LICENSE
Project-URL: Homepage, https://github.com/software-students-spring2025/3-python-package-cravaggio
Project-URL: Repository, https://github.com/software-students-spring2025/3-python-package-cravaggio.git
Project-URL: Bug Tracker, https://github.com/software-students-spring2025/3-python-package-cravaggio/issues
Keywords: fortune cookie
License-File: LICENSE
Provides-Extra: dev
Requires-Dist: pytest; extra == "dev"
Dynamic: author
Dynamic: home-page
Dynamic: license-file
